sophize_datamodel/__init__.py
sophize_datamodel/resource_utils.py
sophize_datamodel/resources.py
sophize_datamodel-0.3.0.dist-info/LICENSE
sophize_datamodel-0.3.0.dist-info/METADATA
sophize_datamodel-0.3.0.dist-info/WHEEL
sophize_datamodel-0.3.0.dist-info/top_level.txt
sophize_datamodel-0.3.0.dist-info/RECORD
