Metadata-Version: 2.1
Name: sophize-datamodel
Version: 0.3.0
Summary: Classes for data can be ingested by Sophize.
Home-page: https://github.com/Sophize/datamodel-python
Author: Abhishek Chugh
Author-email: achugh89@gmail.com
License: MIT
Platform: UNKNOWN
Classifier: License :: OSI Approved :: MIT License
Classifier: Programming Language :: Python :: 3
Classifier: Programming Language :: Python :: 3.7
